apilib/__init__.py
apilib/auth.py
apilib/commands.py
apilib/core.py
apilib/crypto.py
apilib/password_commands.py
apilib/storage.py
apilibrary-1.4.0.dist-info/licenses/LICENSE
apilibrary-1.4.0.dist-info/METADATA
apilibrary-1.4.0.dist-info/WHEEL
apilibrary-1.4.0.dist-info/entry_points.txt
apilibrary-1.4.0.dist-info/top_level.txt
apilibrary-1.4.0.dist-info/RECORD
